k3logging/__init__.py
k3logging/api_impl.py
k3logging-0.1.dist-info/LICENSE
k3logging-0.1.dist-info/METADATA
k3logging-0.1.dist-info/WHEEL
k3logging-0.1.dist-info/top_level.txt
k3logging-0.1.dist-info/RECORD
